uuidt-0.1.1.dist-info/METADATA
uuidt-0.1.1.dist-info/WHEEL
uuidt-0.1.1.dist-info/license_files/LICENSE
uuidt/__init__.py
uuidt/uuidt.abi3.so
uuidt-0.1.1.dist-info/RECORD
