Metadata-Version: 2.1
Name: uuidt
Version: 0.1.1
Classifier: Development Status :: 4 - Beta
Classifier: Intended Audience :: Developers
Classifier: License :: OSI Approved :: MIT License
Classifier: Operating System :: OS Independent
Classifier: Programming Language :: Python
Classifier: Programming Language :: Python :: 3
Classifier: Programming Language :: Python :: 3.7
Classifier: Programming Language :: Python :: 3.8
Classifier: Programming Language :: Python :: 3.9
Classifier: Programming Language :: Python :: 3.10
Classifier: Programming Language :: Python :: 3.11
Classifier: Programming Language :: Python :: 3 :: Only
Classifier: Programming Language :: Rust
Classifier: Programming Language :: Python :: Implementation :: CPython
Classifier: Programming Language :: Python :: Implementation :: PyPy
License-File: LICENSE
Summary: Timestamp-orderable UUIDs for Python, written in Rust.
Author-email: Isaac Harris-Holt <isaac@harris-holt.com>
Maintainer-email: Isaac Harris-Holt <isaac@harris-holt.com>
Requires-Python: >=3.7
Project-URL: repository, https://github.com/isaacharrisholt/uuidt
